cutpaste/__init__.py
cutpaste/cut.py
cutpaste/paste.py
cutpaste/utils.py
cutpaste/version.py
cutpaste-0.0.2.dist-info/METADATA
cutpaste-0.0.2.dist-info/WHEEL
cutpaste-0.0.2.dist-info/entry_points.txt
cutpaste-0.0.2.dist-info/top_level.txt
cutpaste-0.0.2.dist-info/RECORD
