Metadata-Version: 2.1
Name: cutpaste
Version: 0.0.2
Home-page: https://github.com/vik-rant/cutpaste
Classifier: Programming Language :: Python :: 3
Requires-Python: >=3.7
